testhub_mcp/.gitignore
testhub_mcp/PKG-INFO
testhub_mcp/README.md
testhub_mcp/__init__.py
testhub_mcp/api_client.py
testhub_mcp/config.py
testhub_mcp/context.py
testhub_mcp/pyproject.toml
testhub_mcp/server.py
testhub_mcp/resources/__init__.py
testhub_mcp/resources/docs.py
testhub_mcp/tools/__init__.py
testhub_mcp/tools/core.py
testhub_mcp/tools/errors.py
testhub_mcp/tools/suggest.py
testhub_mcp/tools/task.py
testhub_mcp/tools/unified_bug.py
testhub_mcp/tools/unified_docs.py
testhub_mcp/tools/unified_search.py
testhub_mcp/tools/unified_test.py
testhub_mcp-0.1.1.dist-info/METADATA
testhub_mcp-0.1.1.dist-info/WHEEL
testhub_mcp-0.1.1.dist-info/entry_points.txt
testhub_mcp-0.1.1.dist-info/RECORD
