Metadata-Version: 2.4
Name: testhub-mcp
Version: 0.1.1
Summary: TestHub MCP Server - 提供开发任务管理和项目文档集成
Author: TestHub Team
License: MIT
Keywords: cursor,documentation,mcp,testhub
Classifier: Development Status :: 3 - Alpha
Classifier: Intended Audience :: Developers
Classifier: License :: OSI Approved :: MIT License
Classifier: Programming Language :: Python :: 3
Classifier: Programming Language :: Python :: 3.10
Classifier: Programming Language :: Python :: 3.11
Classifier: Programming Language :: Python :: 3.12
Requires-Python: >=3.10
Requires-Dist: httpx>=0.25.0
Requires-Dist: loguru>=0.7.0
Requires-Dist: mcp>=1.0.0
Provides-Extra: all
Requires-Dist: black>=23.0.0; extra == 'all'
Requires-Dist: pytest-asyncio>=0.21.0; extra == 'all'
Requires-Dist: pytest>=7.0.0; extra == 'all'
Requires-Dist: ruff>=0.1.0; extra == 'all'
Requires-Dist: sse-starlette>=1.6.0; extra == 'all'
Requires-Dist: starlette>=0.27.0; extra == 'all'
Requires-Dist: uvicorn>=0.23.0; extra == 'all'
Provides-Extra: dev
Requires-Dist: black>=23.0.0; extra == 'dev'
Requires-Dist: pytest-asyncio>=0.21.0; extra == 'dev'
Requires-Dist: pytest>=7.0.0; extra == 'dev'
Requires-Dist: ruff>=0.1.0; extra == 'dev'
Provides-Extra: sse
Requires-Dist: sse-starlette>=1.6.0; extra == 'sse'
Requires-Dist: starlette>=0.27.0; extra == 'sse'
Requires-Dist: uvicorn>=0.23.0; extra == 'sse'
